[
  {
    "type": "system",
    "text": "MEMORY LEAK [UBUNTU]"
  },
  {
    "type": "system",
    "text": "Operator lane: standard response pressure"
  },
  {
    "type": "info",
    "text": "Mounting production-like service map."
  },
  {
    "type": "warning",
    "text": "Root cause visibility partially degraded."
  },
  {
    "type": "warning",
    "text": "Memory usage critical - OOM imminent"
  },
  {
    "type": "warning",
    "text": "Node.js process memory leak detected"
  },
  {
    "type": "prompt",
    "text": "Press any key to begin..."
  }
]
